xingque-0.2.1.dist-info/METADATA
xingque-0.2.1.dist-info/WHEEL
xingque-0.2.1.dist-info/license_files/LICENSE.txt
xingque.libs/libgcc_s-5b5488a6.so.1
xingque/__init__.py
xingque/__init__.pyi
xingque/py.typed
xingque/xingque.abi3.so
xingque-0.2.1.dist-info/RECORD
