Metadata-Version: 2.3
Name: xingque
Version: 0.2.1
Classifier: Development Status :: 3 - Alpha
Classifier: Intended Audience :: Developers
Classifier: License :: OSI Approved :: Apache Software License
Classifier: Programming Language :: Rust
Classifier: Programming Language :: Python
Classifier: Programming Language :: Python :: Implementation :: CPython
Classifier: Topic :: Software Development :: Interpreters
Classifier: Typing :: Typed
License-File: LICENSE.txt
Summary: Yet another typed Python binding to starlark-rust
Keywords: starlark,starlark-rust,pyo3
Author: WANG Xuerui <git@xen0n.name>
Author-email: WANG Xuerui <git@xen0n.name>
Maintainer-email: WANG Xuerui <git@xen0n.name>
License: Apache-2.0
Requires-Python: >=3.8
Project-URL: homepage, https://github.com/xen0n/xingque
Project-URL: repository, https://github.com/xen0n/xingque
Project-URL: changelog, https://github.com/xen0n/xingque/blob/main/CHANGELOG.md
